README.md
setup.cfg
setup.py
trex_program.egg-info/PKG-INFO
trex_program.egg-info/SOURCES.txt
trex_program.egg-info/dependency_links.txt
trex_program.egg-info/requires.txt
trex_program.egg-info/top_level.txt
trexprogram/__init__.py
trexprogram/membership/__init__.py
trexprogram/referral/__init__.py
trexprogram/referral/referral_program.py
trexprogram/reward_program/__init__.py
trexprogram/reward_program/birthday_reward_program.py
trexprogram/reward_program/giveaway_new_joined_membership_reward_program.py
trexprogram/reward_program/giveaway_reward_program.py
trexprogram/reward_program/lucky_draw_program.py
trexprogram/reward_program/point_reward_program.py
trexprogram/reward_program/prepaid_program.py
trexprogram/reward_program/promotion_reward_program.py
trexprogram/reward_program/reward_program_base.py
trexprogram/reward_program/reward_program_factory.py
trexprogram/reward_program/stamp_reward_program.py
trexprogram/reward_program/tier_reward_program.py
trexprogram/reward_program/voucher_reward_program.py
trexprogram/utils/__init__.py
trexprogram/utils/reward_program_helper.py
trexprogram/utils/tier_reward_program_helper.py