Metadata-Version: 2.1
Name: trex-program
Version: 1.6.3
Summary: TRex Program package
Home-page: https://bitbucket.org/lokjac/trex-program
Author: Jack Lok
Author-email: sglok77@gmail.com
Classifier: Programming Language :: Python :: 3
Classifier: License :: OSI Approved :: MIT License
Classifier: Operating System :: OS Independent
Requires-Dist: trex-lib
Requires-Dist: trex-model
